fds/__init__.py
fds/sdk/__init__.py
fds/sdk/DirectStreamingofTransactionMessages/__init__.py
fds/sdk/DirectStreamingofTransactionMessages/api_client.py
fds/sdk/DirectStreamingofTransactionMessages/configuration.py
fds/sdk/DirectStreamingofTransactionMessages/exceptions.py
fds/sdk/DirectStreamingofTransactionMessages/model_utils.py
fds/sdk/DirectStreamingofTransactionMessages/rest.py
fds/sdk/DirectStreamingofTransactionMessages/api/__init__.py
fds/sdk/DirectStreamingofTransactionMessages/api/dsotm_api.py
fds/sdk/DirectStreamingofTransactionMessages/apis/__init__.py
fds/sdk/DirectStreamingofTransactionMessages/model/__init__.py
fds/sdk/DirectStreamingofTransactionMessages/model/additional_field.py
fds/sdk/DirectStreamingofTransactionMessages/model/client_error_response.py
fds/sdk/DirectStreamingofTransactionMessages/model/dsotm_parameters.py
fds/sdk/DirectStreamingofTransactionMessages/model/dsotm_parameters_root.py
fds/sdk/DirectStreamingofTransactionMessages/model/error.py
fds/sdk/DirectStreamingofTransactionMessages/model/error_source.py
fds/sdk/DirectStreamingofTransactionMessages/model/execution.py
fds/sdk/DirectStreamingofTransactionMessages/model/order.py
fds/sdk/DirectStreamingofTransactionMessages/model/placement.py
fds/sdk/DirectStreamingofTransactionMessages/models/__init__.py
fds.sdk.DirectStreamingofTransactionMessages-1.0.1.dist-info/LICENSE
fds.sdk.DirectStreamingofTransactionMessages-1.0.1.dist-info/METADATA
fds.sdk.DirectStreamingofTransactionMessages-1.0.1.dist-info/WHEEL
fds.sdk.DirectStreamingofTransactionMessages-1.0.1.dist-info/top_level.txt
fds.sdk.DirectStreamingofTransactionMessages-1.0.1.dist-info/RECORD
